BelDigitalHandwriting/BelDHAnalyser.py
BelDigitalHandwriting/Symbol.py
BelDigitalHandwriting/WordSentence.py
BelDigitalHandwriting/__init__.py
BelDigitalHandwriting/constants.py
BelDigitalHandwriting/Models/AnalyzeModels.py
BelDigitalHandwriting/Models/SymbolModels.py
BelDigitalHandwriting/Models/WordSentenceModels.py
BelDigitalHandwriting/slouniki_parsed/chastica.txt
BelDigitalHandwriting/slouniki_parsed/dzeeprymetnik.txt
BelDigitalHandwriting/slouniki_parsed/dzeeprysloue.txt
BelDigitalHandwriting/slouniki_parsed/dzeyaslou.txt
BelDigitalHandwriting/slouniki_parsed/lychebnik.txt
BelDigitalHandwriting/slouniki_parsed/nazounik.txt
BelDigitalHandwriting/slouniki_parsed/pabochnae_slova.txt
BelDigitalHandwriting/slouniki_parsed/predycatiu.txt
BelDigitalHandwriting/slouniki_parsed/prymetnik.txt
BelDigitalHandwriting/slouniki_parsed/prynazounik.txt
BelDigitalHandwriting/slouniki_parsed/prysloue.txt
BelDigitalHandwriting/slouniki_parsed/vyklichnik.txt
BelDigitalHandwriting/slouniki_parsed/zaymenik.txt
BelDigitalHandwriting/slouniki_parsed/zluchnik.txt
bel_digital_handwriting_py-0.0.5.dist-info/LICENSE
bel_digital_handwriting_py-0.0.5.dist-info/METADATA
bel_digital_handwriting_py-0.0.5.dist-info/WHEEL
bel_digital_handwriting_py-0.0.5.dist-info/top_level.txt
bel_digital_handwriting_py-0.0.5.dist-info/RECORD
