Metadata-Version: 2.1
Name: bel-digital-handwriting-py
Version: 0.0.5
Summary: Пакет для аналіза беларускіх тэкстаў і вызначэння лічбавага почырку пісьменніка
Home-page: https://github.com/Kononenko-Daniil/bel-digital-handwriting-py
Author: Daniil Kononenko
License: MIT
Project-URL: Source, https://github.com/Kononenko-Daniil/bel-digital-handwriting-py
License-File: LICENSE
